COPYING
COPYING.LGPL
MANIFEST.in
README
pavement.py
paver-minilib.zip
setup.cfg
setup.py
setup_win.py
uRSSus.desktop
urssus.e4p
uRSSus.egg-info/PKG-INFO
uRSSus.egg-info/SOURCES.txt
uRSSus.egg-info/dependency_links.txt
uRSSus.egg-info/entry_points.txt
uRSSus.egg-info/requires.txt
uRSSus.egg-info/top_level.txt
urssus/__init__.py
urssus/client.py
urssus/config.py
urssus/database.py
urssus/dbtables.py
urssus/feedtree.py
urssus/feedupdater.py
urssus/globals.py
urssus/main.py
urssus/norm.py
urssus/postmodel.py
urssus/processdialog.py
urssus/schema.py
urssus/urssus.py
urssus/images/1downarrow.svg
urssus/images/1leftarrow.svg
urssus/images/1rightarrow.svg
urssus/images/2downarrow.svg
urssus/images/apply.svg
urssus/images/bug.svg
urssus/images/configure.svg
urssus/images/edit.svg
urssus/images/editclear.svg
urssus/images/editcopy.svg
urssus/images/editdelete.svg
urssus/images/exit.svg
urssus/images/file_broken.svg
urssus/images/filenew.svg
urssus/images/find.svg
urssus/images/flag.svg
urssus/images/folder.svg
urssus/images/folder_new.svg
urssus/images/gear.svg
urssus/images/icons.qrc
urssus/images/mail_generic.svg
urssus/images/menubar.svg
urssus/images/star.svg
urssus/images/star2.svg
urssus/images/stop.svg
urssus/images/sync.svg
urssus/images/tag.svg
urssus/images/twitter.svg
urssus/images/urssus-unread.svg
urssus/images/urssus.jpg
urssus/images/urssus.png
urssus/images/urssus.svg
urssus/images/view_detailed.svg
urssus/images/view_left_right.svg
urssus/images/view_top_bottom.svg
urssus/images/viewmag+.svg
urssus/images/viewmag-.svg
urssus/images/window_fullscreen.svg
urssus/templates/__init__.py
urssus/templates/combined.tmpl
urssus/templates/fancy.tmpl
urssus/templates/feed.tmpl
urssus/templates/mootools-core.js
urssus/templates/mootools-more.js
urssus/templates/post.tmpl
urssus/templates/style.css
urssus/ui/Ui_about.py
urssus/ui/Ui_bugdialog.py
urssus/ui/Ui_configdialog.py
urssus/ui/Ui_fancyauth.py
urssus/ui/Ui_feed_properties.py
urssus/ui/Ui_filterwidget.py
urssus/ui/Ui_greaderimport.py
urssus/ui/Ui_main.py
urssus/ui/Ui_newfeed.py
urssus/ui/Ui_runprocess.py
urssus/ui/Ui_searchwidget.py
urssus/ui/Ui_twitterpost.py
urssus/ui/__init__.py
