Metadata-Version: 1.0
Name: uRSSus
Version: 0.2.13
Summary: A multiplatform GUI news agregator.
Home-page: http://urssus.googlecode.com
Author: Roberto Alsina
Author-email: ralsina@netmanagers.com.ar
License: GPLv2
Keywords: atom rss pyqt
Platform: UNKNOWN
